nonebot_plugin_lostark_wandering_trader/__init__.py
nonebot_plugin_lostark_wandering_trader/config.py
nonebot_plugin_lostark_wandering_trader/display_at.py
nonebot_plugin_lostark_wandering_trader/display_get.py
nonebot_plugin_lostark_wandering_trader-0.2.6.dist-info/LICENSE
nonebot_plugin_lostark_wandering_trader-0.2.6.dist-info/METADATA
nonebot_plugin_lostark_wandering_trader-0.2.6.dist-info/WHEEL
nonebot_plugin_lostark_wandering_trader-0.2.6.dist-info/top_level.txt
nonebot_plugin_lostark_wandering_trader-0.2.6.dist-info/RECORD
