Metadata-Version: 2.1
Name: nonebot-plugin-lostark-wandering-trader
Version: 0.2.6
Summary: NoneBot lostark cn wandering trader plugin
Home-page: https://github.com/EmiyaGm/nonebot-plugin-lostark-wandering-trader
Author: EmiyaGm
Author-email: EmiyaGm <464723943@qq.com>
License: MIT License
Project-URL: Homepage, https://github.com/EmiyaGm/nonebot-plugin-lostark-wandering-trader
Project-URL: Bug Tracker, https://github.com/EmiyaGm/nonebot-plugin-lostark-wandering-trader/issues
Classifier: Programming Language :: Python :: 3
Classifier: License :: OSI Approved :: MIT License
Classifier: Operating System :: OS Independent
Requires-Python: >=3.8,<4.0
License-File: LICENSE
Requires-Dist: httpx <1.0.0,>=0.18.0
Requires-Dist: nonebot-plugin-apscheduler >=0.3.0
Requires-Dist: nonebot-adapter-onebot >=2.0.0
Requires-Dist: nonebot2[fastapi] >=2.0.0
